skillz/__init__.py
skillz/__main__.py
skillz/_server.py
skillz/_version.py
skillz-0.1.14.dist-info/WHEEL
skillz-0.1.14.dist-info/entry_points.txt
skillz-0.1.14.dist-info/METADATA
skillz-0.1.14.dist-info/RECORD
